django_cart/__init__.py
django_cart/admin.py
django_cart/apps.py
django_cart/models.py
django_cart/tests.py
django_cart/urls.py
django_cart/views.py
django_cart/migrations/0001_initial.py
django_cart/migrations/0002_delete_product.py
django_cart/migrations/__init__.py
django_cart/templatetags/__init__.py
django_cart/templatetags/cart_tag.py
django_cart/utils/__init__.py
django_cart/utils/utils.py
django_cart/utils/wrapper.py
django_new_cart-1.1.0.dist-info/LICENSE
django_new_cart-1.1.0.dist-info/METADATA
django_new_cart-1.1.0.dist-info/WHEEL
django_new_cart-1.1.0.dist-info/top_level.txt
django_new_cart-1.1.0.dist-info/RECORD
