Metadata-Version: 2.1
Name: django-new-cart
Version: 1.1.0
Summary: Easy to use django shopping multi cart.
Home-page: https://github.com/n4b3ts3/django-cart
Author: Esteban Chacon Martin
Author-email: n4b3ts3@gmail.com
Project-URL: Bug Tracker, https://github.com/n4b3ts3/django-cart/issues
Keywords: django,shop,cart,management,multi cart
Classifier: Framework :: Django
Classifier: Programming Language :: Python :: 3
Classifier: Operating System :: OS Independent
Classifier: License :: OSI Approved :: GNU General Public License (GPL)
Requires-Python: >=3.6
License-File: LICENSE
